---
title: 单例模式
date: 2023-09-03 20:00:32
categories:
  - [设计模式, 单例模式]
tags:
  - design patterns
  - creational
  - singleton
---

## 单例模式

### 意图

保证一个类只有一个实例，并且为它提供一个全局访问点。

### 适用场景

- 线程池、连接池
- 缓存管理器
- 日志记录器
- 文件管理器
- ......

<!-- more -->

### 典型案例

- [java.lang.Runtime#getRuntime()](http://docs.oracle.com/javase/8/docs/api/java/lang/Runtime.html#getRuntime%28%29)
- [Spring ConfigurableBeanFactory#SCOPE_SINGLETON](https://docs.spring.io/spring-framework/docs/5.3.29/javadoc-api/org/springframework/beans/factory/config/ConfigurableBeanFactory.html#SCOPE_SINGLETON)

### 代码示例

#### 饿汉式单例

```java
public class HungrySingleton implements Serializable {

    // 类装载时就完成了初始化，jvm保证线程安全问题。若从始至终没有使用实例，会造成内存浪费。
    private static final HungrySingleton INSTANCE = new HungrySingleton();

    // 可被反射破坏单例性！！！
    private HungrySingleton() {
    }

    public static HungrySingleton getInstance() {
        return INSTANCE;
    }

    // 实现Serializable的类需要添加该方法，防止反序列化实例时创建新的实例。（下同）
    private Object readResolve(){
        return INSTANCE;
    }
}
```

#### 懒汉式单例

```java
public class LazySingleton {

    /**
    volatile修饰，禁止jvm指令重排序（即禁止重排21,24）：

    getInstance() 方法部分字节码：
    10 monitorenter
    11 getstatic #2 <com/jd/study/designpattern/singleton/LazySingleton.instance>
    14 ifnonnull 27 (+13)
    17 new #3 <com/jd/study/designpattern/singleton/LazySingleton>
    20 dup
    21 invokespecial #4 <com/jd/study/designpattern/singleton/LazySingleton.<init>>
    24 putstatic #2 <com/jd/study/designpattern/singleton/LazySingleton.instance>
    27 aload_0
    28 monitorexit
     */
    private static volatile LazySingleton instance;

    private LazySingleton() {
    }

    public static LazySingleton getInstance() {
        if (instance == null) { // 双重检查为了不必要的加锁
            synchronized (LazySingleton.class) {
                if (instance == null) {
                    instance = new LazySingleton();
                }
            }
        }
        return instance;
    }

    private Object readResolve() {
        return instance;
    }
}
```

#### 静态内部类单例

```java
public class StaticInnerClassSingleton {

    // 可被反射破坏单例性！！！
    private StaticInnerClassSingleton() {}

    public static StaticInnerClassSingleton getInstance() {
        return SingletonHolder.INSTANCE;
    }

    // 首先类加载时，内部类不会马上被加载，所以不会事先占用内存空间，其次在初始化内部类的过程中，jvm会保证同一时刻只有一个线程运行。
    public static class SingletonHolder {

        public static final StaticInnerClassSingleton INSTANCE = new StaticInnerClassSingleton();
    }

    private Object readResolve() {
        return SingletonHolder.INSTANCE;
    }
}
```

#### 枚举类单例

```java
public enum EnumSingleton {

    /**
    通过javap -v EnumSingleton.class可以看到HOLDER其实是static final类型的，由jvm保证线程安全问题：

    public static final com.xxx.designpattern.singleton.EnumSingleton HOLDER;
        descriptor: Lcom/xxx/designpattern/singleton/EnumSingleton;
        flags: ACC_PUBLIC, ACC_STATIC, ACC_FINAL, ACC_ENUM
     */
    HOLDER(0);

    private int code;

    // Enum 类不允许反射构造，调用报错：java.lang.IllegalArgumentException: Cannot reflectively create enum objects。
    EnumSingleton(int code) {
        this.code = code;
    }

    public int getCode() {
        return code;
    }
}
```

```java java.lang.Enum
public abstract class Enum<E extends Enum<E>> implements Comparable<E>, Serializable {

    // 略...

    // Enum 类不允许克隆。
    protected final Object clone() throws CloneNotSupportedException {
        throw new CloneNotSupportedException();
    }

    // Enum 类不允许反序列化。
    private void readObject(ObjectInputStream var1) throws IOException, ClassNotFoundException {
        throw new InvalidObjectException("can't deserialize enum");
    }

    private void readObjectNoData() throws ObjectStreamException {
        throw new InvalidObjectException("can't deserialize enum");
    }
}
```

### 类图

{% asset_img singleton.png %}

> [示例代码]()
